[
  {
    "id": 1,
    "name": "Bột muối dạ dày Nabicar-AC gói 100g Á Châu",
    "specification": "Gói 100g",
    "category1": "Thực phẩm chức năng",
    "category2": "Tiêu Hóa Gan Mật",
    "registration_num": "11061/2019/ĐKSP",
    "price": 70000,
    "original_price": 70000,
    "image": "assets/placeholder.png",
    "in_stock": true,
    "rating": 4.2,
    "sold_count": 12
  },
  {
    "id": 2,
    "name": "Valiera 2mg Hộp 1 Vỉ x 30 Viên nén bao phim Abbott",
    "specification": "Hộp 1 vỉ 30 viên",
    "category1": "Thuốc kê đơn",
    "category2": "Thuốc tiết niệu - sinh dục",
    "registration_num": "VN-19225-15",
    "price": 140000,
    "original_price": 160000,
    "image": "assets/placeholder.png",
    "in_stock": true,
    "rating": 4.9,
    "sold_count": 89
  },
  {
    "id": 3,
    "name": "Elthon 50mg Hộp 2 vỉ x 10 viên nén Abbott",
    "specification": "Hộp 2 Vỉ x 10 Viên",
    "category1": "Thuốc kê đơn",
    "category2": "Thuốc tiêu hóa - gan mật",
    "registration_num": "VN-8408-09",
    "price": 80000,
    "original_price": 100000,
    "image": "assets/placeholder.png",
    "in_stock": true,
    "rating": 4.8,
    "sold_count": 158
  },
  {
    "id": 4,
    "name": "Rabe-G 20mg Hộp 3 vỉ x 10 viên nén bao phim tan trong ruột Abbott",
    "specification": "Hộp 3 vỉ x 10 viên",
    "category1": "Thuốc kê đơn",
    "category2": "Thuốc tiêu hóa - gan mật",
    "registration_num": "893110091524",
    "price": 150000,
    "original_price": 150000,
    "image": "assets/placeholder.png",
    "in_stock": false,
    "rating": 4.5,
    "sold_count": 95
  },
  {
    "id": 5,
    "name": "Sữa GLUCERNA hương vani chai 220ml Abbott",
    "specification": "Chai",
    "category1": "Hàng tiêu dùng",
    "category2": "Chăm sóc cá nhân",
    "registration_num": "10/2023/ĐKSP",
    "price": 180000,
    "original_price": 180000,
    "image": "assets/placeholder.png",
    "in_stock": true,
    "rating": 4.3,
    "sold_count": 173
  },
  {
    "id": 6,
    "name": "Betaserc 16mg Hộp 3 vỉ x 20 viên nén Abbott",
    "specification": "Hộp 3 vỉ x 20 viên nén",
    "category1": "Thuốc kê đơn",
    "category2": "Thuốc tim mạch - máu",
    "registration_num": "VN-17206-13",
    "price": 90000,
    "original_price": 90000,
    "image": "assets/placeholder.png",
    "in_stock": true,
    "rating": 4.4,
    "sold_count": 84
  },
  {
    "id": 7,
    "name": "Duphaston 10mg Hộp 1 vỉ x 20 viên nén Abbott",
    "specification": "Hộp 1 Vỉ x 20 Viên",
    "category1": "Thuốc kê đơn",
    "category2": "Thuốc tiết niệu - sinh dục",
    "registration_num": "870110067423",
    "price": 190000,
    "original_price": 190000,
    "image": "assets/placeholder.png",
    "in_stock": true,
    "rating": 4.4,
    "sold_count": 34
  },
  {
    "id": 8,
    "name": "Betaserc 24mg Hộp 5 vỉ x 10 viên nén Abbott",
    "specification": "Hộp 5 vỉ x 10 viên nén",
    "category1": "Thuốc kê đơn",
    "category2": "Thuốc tim mạch - máu",
    "registration_num": "300110779724",
    "price": 170000,
    "original_price": 190000,
    "image": "assets/placeholder.png",
    "in_stock": true,
    "rating": 4.7,
    "sold_count": 187
  },
  {
    "id": 9,
    "name": "Sữa Ensure Gold StrengthPro hương vani chai 237ml Abbott",
    "specification": "chai 237ml",
    "category1": "Hàng tiêu dùng",
    "category2": "Chăm sóc cá nhân",
    "registration_num": "09/2023/ĐKSP",
    "price": 110000,
    "original_price": 130000,
    "image": "assets/placeholder.png",
    "in_stock": true,
    "rating": 4.1,
    "sold_count": 201
  },
  {
    "id": 10,
    "name": "Duphalac Hộp 20 gói x 15ml Abbott",
    "specification": "hộp 20 gói x 15 ml",
    "category1": "Thuốc không kê đơn",
    "category2": "Thuốc tiêu hóa - gan mật",
    "registration_num": "870100067323",
    "price": 80000,
    "original_price": 100000,
    "image": "assets/placeholder.png",
    "in_stock": true,
    "rating": 4.8,
    "sold_count": 88
  },
  {
    "id": 11,
    "name": "Klacid MR Hộp 1 Vỉ x 5 Viên nén giải phóng biến đổi Abbott",
    "specification": "Hộp 1 vỉ x 5 Viên",
    "category1": "Thuốc kê đơn",
    "category2": "Thuốc kháng sinh",
    "registration_num": "800110982024",
    "price": 190000,
    "original_price": 190000,
    "image": "assets/placeholder.png",
    "in_stock": true,
    "rating": 4.9,
    "sold_count": 39
  },
  {
    "id": 12,
    "name": "Klacid 250mg Hộp 1 vỉ x 10 viên nén Abbott",
    "specification": "Hộp 1 vỉ x 10 viên",
    "category1": "Thuốc kê đơn",
    "category2": "Thuốc kháng sinh",
    "registration_num": "800110779624",
    "price": 50000,
    "original_price": 70000,
    "image": "assets/placeholder.png",
    "in_stock": false,
    "rating": 4.5,
    "sold_count": 115
  },
  {
    "id": 13,
    "name": "Klacid 125mg/5ml Hộp 1 lọ 60ml cốm pha hỗn dịch uống Abbott",
    "specification": "Hộp 1 Chai X 60ml",
    "category1": "Thuốc kê đơn",
    "category2": "Thuốc kháng sinh",
    "registration_num": "899110399323",
    "price": 70000,
    "original_price": 70000,
    "image": "assets/placeholder.png",
    "in_stock": true,
    "rating": 4.2,
    "sold_count": 112
  },
  {
    "id": 14,
    "name": "Abmexic 7.5 Hộp 3 vỉ x 10 viên nén Abbott",
    "specification": "Hộp 3 vỉ x 10 viên",
    "category1": "Thuốc kê đơn",
    "category2": "Chống viêm, giảm sưng phù nề",
    "registration_num": "VD-22846-15",
    "price": 60000,
    "original_price": 60000,
    "image": "assets/placeholder.png",
    "in_stock": true,
    "rating": 4.6,
    "sold_count": 26
  },
  {
    "id": 15,
    "name": "Glotadol 500 Hộp 10 vỉ x 10 viên nén dài bao phim Abbott",
    "specification": "Hộp 10 vỉ x 10 viên",
    "category1": "Thuốc không kê đơn",
    "category2": "Giảm đau hạ sốt",
    "registration_num": "VD-22851-15",
    "price": 80000,
    "original_price": 100000,
    "image": "assets/placeholder.png",
    "in_stock": true,
    "rating": 4.8,
    "sold_count": 88
  },
  {
    "id": 16,
    "name": "Glotadol 250mg Hộp 20 gói x 2,5 gam Abbott",
    "specification": "Hộp 20 gói",
    "category1": "Thuốc không kê đơn",
    "category2": "Giảm đau hạ sốt",
    "registration_num": "VD-22459-15",
    "price": 90000,
    "original_price": 90000,
    "image": "assets/placeholder.png",
    "in_stock": true,
    "rating": 4.4,
    "sold_count": 114
  },
  {
    "id": 17,
    "name": "Glotadol 150mg Hộp 20 gói x 2 gam Abbott",
    "specification": "Hộp 20 gói",
    "category1": "Thuốc không kê đơn",
    "category2": "Giảm đau hạ sốt",
    "registration_num": "893100091324",
    "price": 80000,
    "original_price": 100000,
    "image": "assets/placeholder.png",
    "in_stock": true,
    "rating": 4.8,
    "sold_count": 38
  },
  {
    "id": 18,
    "name": "Glogyl Hộp 2 vỉ x 10 viên nén Abbott",
    "specification": "Hộp 2 Vỉ x 10 Viên",
    "category1": "Thuốc kê đơn",
    "category2": "Thuốc kháng sinh",
    "registration_num": "893115326323",
    "price": 150000,
    "original_price": 150000,
    "image": "assets/placeholder.png",
    "in_stock": false,
    "rating": 4.0,
    "sold_count": 10
  },
  {
    "id": 19,
    "name": "Glomoti-M 10mg Hộp 10 vỉ x 10 viên nén bao phim Glomed",
    "specification": "Hộp 10 Vỉ x 10 Viên",
    "category1": "Thuốc kê đơn",
    "category2": "Thuốc tiêu hóa - gan mật",
    "registration_num": "893110324323",
    "price": 140000,
    "original_price": 160000,
    "image": "assets/placeholder.png",
    "in_stock": true,
    "rating": 4.9,
    "sold_count": 159
  },
  {
    "id": 20,
    "name": "Brufen 100mg/5ml hương cam Hộp 1 lọ x 60ml Abbott",
    "specification": "hộp 1 lọ x 60ml",
    "category1": "Thuốc không kê đơn",
    "category2": "Thuốc giảm đau, hạ sốt, kháng viêm",
    "registration_num": "899100000324",
    "price": 80000,
    "original_price": 100000,
    "image": "assets/placeholder.png",
    "in_stock": true,
    "rating": 4.3,
    "sold_count": 133
  },
  {
    "id": 21,
    "name": "Máy đo đường huyết On Call Plus",
    "specification": "Hộp 1 máy",
    "category1": "Trang thiết bị Y tế",
    "category2": "Máy Móc Và Thiết Bị Đo",
    "registration_num": "40 PL-MDC-PCBPL-BYT",
    "price": 170000,
    "original_price": 190000,
    "image": "assets/placeholder.png",
    "in_stock": true,
    "rating": 4.2,
    "sold_count": 52
  },
  {
    "id": 22,
    "name": "Que thử đường huyết On Call Plus Hộp 2 lọ x 25 que Acon",
    "specification": "Hộp 50 que",
    "category1": "Trang thiết bị Y tế",
    "category2": "Máy Móc Và Thiết Bị Đo",
    "registration_num": "170000360/PCBMB-HCM",
    "price": 120000,
    "original_price": 120000,
    "image": "assets/placeholder.png",
    "in_stock": true,
    "rating": 4.2,
    "sold_count": 82
  },
  {
    "id": 23,
    "name": "Lactéol 340mg Hộp 10 gói Adare",
    "specification": "Hộp 10 Gói",
    "category1": "Thuốc không kê đơn",
    "category2": "Thuốc tiêu hóa - gan mật",
    "registration_num": "QLSP-906-15",
    "price": 50000,
    "original_price": 70000,
    "image": "assets/placeholder.png",
    "in_stock": false,
    "rating": 4.5,
    "sold_count": 35
  },
  {
    "id": 24,
    "name": "Tabifobed-New Hộp 1 vỉ x 10 viên nang cứng ADPharm",
    "specification": "Hộp 1 vỉ x 10 viên nang cứng",
    "category1": "Thuốc không kê đơn",
    "category2": "Thuốc dị ứng và miễn dịch",
    "registration_num": "VD-34253-20.",
    "price": 160000,
    "original_price": 160000,
    "image": "assets/placeholder.png",
    "in_stock": true,
    "rating": 4.1,
    "sold_count": 201
  },
  {
    "id": 25,
    "name": "Lột mụn cám lô hội Mayan Skincare Hộp 4 miếng",
    "specification": "Hộp 4 miếng",
    "category1": "Trang thiết bị Y tế",
    "category2": "Chăm sóc cá nhân",
    "registration_num": "160822/21/CBMP-QLD",
    "price": 90000,
    "original_price": 90000,
    "image": "assets/placeholder.png",
    "in_stock": true,
    "rating": 4.9,
    "sold_count": 109
  },
  {
    "id": 26,
    "name": "Lột mụn Power nose cleaning strips charcoal Hộp 4 miếng",
    "specification": "Hộp 4 miếng",
    "category1": "Mỹ phẩm",
    "category2": "Chăm sóc sắc đẹp",
    "registration_num": "101897/19/CBMP-QLD",
    "price": 190000,
    "original_price": 190000,
    "image": "assets/placeholder.png",
    "in_stock": true,
    "rating": 4.9,
    "sold_count": 69
  },
  {
    "id": 27,
    "name": "Kem đánh răng cao cấp Hàn Quốc 2080 Dongyi Shenggum Hộp 1 tuýp x 120g",
    "specification": "Tuýp 120g",
    "category1": "Hàng tiêu dùng",
    "category2": "Chăm sóc cá nhân",
    "registration_num": "146768/21/CBMP-QLD",
    "price": 190000,
    "original_price": 190000,
    "image": "assets/placeholder.png",
    "in_stock": true,
    "rating": 4.4,
    "sold_count": 184
  },
  {
    "id": 28,
    "name": "Diếp cá thảo dược Hộp 3 vỉ x 10 viên Akopha",
    "specification": "Hộp 3 vỉ x 10 viên",
    "category1": "Thực phẩm chức năng",
    "category2": "Vitamin và khoáng chất",
    "registration_num": "1483/2018/ĐKSP",
    "price": 180000,
    "original_price": 180000,
    "image": "assets/placeholder.png",
    "in_stock": true,
    "rating": 4.8,
    "sold_count": 98
  },
  {
    "id": 29,
    "name": "Diếp cá thảo dược Hộp 1 lọ x 30 viên Akopha",
    "specification": "Hộp 1 lọ x 30 viên",
    "category1": "Thực phẩm chức năng",
    "category2": "Vitamin và khoáng chất",
    "registration_num": "1483/2018/ĐKSP",
    "price": 140000,
    "original_price": 160000,
    "image": "assets/placeholder.png",
    "in_stock": true,
    "rating": 4.9,
    "sold_count": 59
  },
  {
    "id": 30,
    "name": "Bổ sung chất điện giải Orizoll pluss Tuýp x 10 viên nén sủi Akopha",
    "specification": "Tuýp x 10 viên nén sủi",
    "category1": "Thực phẩm chức năng",
    "category2": "Vitamin và khoáng chất",
    "registration_num": "4661/2018/ĐKSP",
    "price": 190000,
    "original_price": 190000,
    "image": "assets/placeholder.png",
    "in_stock": true,
    "rating": 4.9,
    "sold_count": 129
  },
  {
    "id": 31,
    "name": "Trí não Brain DHA Hộp 20 gói x 3g Akopha",
    "specification": "Hộp 20 gói",
    "category1": "Thực phẩm chức năng",
    "category2": "Vitamin và khoáng chất",
    "registration_num": "12781/2020/ĐKSP",
    "price": 150000,
    "original_price": 150000,
    "image": "assets/placeholder.png",
    "in_stock": false,
    "rating": 4.5,
    "sold_count": 95
  },
  {
    "id": 32,
    "name": "Liquid Calcium+D3 Hộp 1 lọ x 30 viên nang mềm Akopha",
    "specification": "Hộp 1 lọ x 30 viên nang mềm",
    "category1": "Thực phẩm chức năng",
    "category2": "Vitamin và khoáng chất",
    "registration_num": "7380/2018/ĐKSP",
    "price": 90000,
    "original_price": 90000,
    "image": "assets/placeholder.png",
    "in_stock": true,
    "rating": 4.4,
    "sold_count": 194
  },
  {
    "id": 33,
    "name": "Biotin 5mg Hộp 20 viên nén bao phim Akopha",
    "specification": "Hộp 2 vỉ x 10 viên",
    "category1": "Thuốc không kê đơn",
    "category2": "Vitamin và khoáng chất",
    "registration_num": "",
    "price": 100000,
    "original_price": 100000,
    "image": "assets/placeholder.png",
    "in_stock": false,
    "rating": 4.5,
    "sold_count": 145
  },
  {
    "id": 34,
    "name": "Derma Forte Hộp 1 tuýp 15g Alcom",
    "specification": "Hộp 1 tuýp 15g",
    "category1": "Thuốc không kê đơn",
    "category2": "Da liễu",
    "registration_num": "002830/14/CBMP-HCM",
    "price": 140000,
    "original_price": 160000,
    "image": "assets/placeholder.png",
    "in_stock": true,
    "rating": 4.4,
    "sold_count": 84
  },
  {
    "id": 35,
    "name": "Dung dịch nhỏ mắt Systane Ultra hộp 1 chai 5ml Alcon",
    "specification": "Chai 5ml",
    "category1": "Thuốc không kê đơn",
    "category2": "Mắt",
    "registration_num": "VN-19762-16",
    "price": 70000,
    "original_price": 70000,
    "image": "assets/placeholder.png",
    "in_stock": true,
    "rating": 4.2,
    "sold_count": 12
  },
  {
    "id": 36,
    "name": "Dung dịch nhỏ mắt Systane Ultra Hộp 1 chai 10ml Alcon",
    "specification": "Hộp 1 chai 10ml",
    "category1": "Thuốc không kê đơn",
    "category2": "Mắt",
    "registration_num": "VN-19762-16",
    "price": 90000,
    "original_price": 90000,
    "image": "assets/placeholder.png",
    "in_stock": true,
    "rating": 4.4,
    "sold_count": 144
  },
  {
    "id": 37,
    "name": "Sữa rửa mặt Gammaphil Gentle Skin Cleanser Chai 125ml Alcon",
    "specification": "Chai 125ml",
    "category1": "Mỹ phẩm",
    "category2": "Chăm sóc cá nhân",
    "registration_num": "000669/21/CBMP-HCM",
    "price": 130000,
    "original_price": 130000,
    "image": "assets/placeholder.png",
    "in_stock": true,
    "rating": 4.3,
    "sold_count": 113
  },
  {
    "id": 38,
    "name": "Sữa rửa mặt Gammaphil Gentle Skin Cleanser Chai 500ml Alcon",
    "specification": "Chai 500ml",
    "category1": "Mỹ phẩm",
    "category2": "Chăm sóc cá nhân",
    "registration_num": "000669/21/CBMP-HCM",
    "price": 190000,
    "original_price": 190000,
    "image": "assets/placeholder.png",
    "in_stock": true,
    "rating": 4.4,
    "sold_count": 144
  },
  {
    "id": 39,
    "name": "Tăm chỉ nha khoa OKAMURA hộp 140 chiếc",
    "specification": "hộp 140 chiếc",
    "category1": "Hàng tiêu dùng",
    "category2": "Chăm sóc cá nhân",
    "registration_num": "",
    "price": 150000,
    "original_price": 150000,
    "image": "assets/placeholder.png",
    "in_stock": false,
    "rating": 4.0,
    "sold_count": 190
  },
  {
    "id": 40,
    "name": "Refresh Tears Hộp 1 chai 15ml Allergan",
    "specification": "Hộp 1 chai 15ml",
    "category1": "Thuốc không kê đơn",
    "category2": "Mắt",
    "registration_num": "VN-19386-15",
    "price": 110000,
    "original_price": 130000,
    "image": "assets/placeholder.png",
    "in_stock": true,
    "rating": 4.1,
    "sold_count": 121
  },
  {
    "id": 41,
    "name": "Viên sủi Ion+ Sport Drink 3 Tuýp 20 viên Alpha",
    "specification": "Tuýp 20 viên",
    "category1": "Thực phẩm chức năng",
    "category2": "Vitamin và khoáng chất",
    "registration_num": "28/Alpha/2022",
    "price": 160000,
    "original_price": 160000,
    "image": "assets/placeholder.png",
    "in_stock": true,
    "rating": 4.1,
    "sold_count": 41
  },
  {
    "id": 42,
    "name": "Viên sủi Plusszs Energy hương bò húc Tuýp 20 viên Alpha",
    "specification": "Tuýp 20 viên",
    "category1": "Thực phẩm chức năng",
    "category2": "Vitamin và khoáng chất",
    "registration_num": "13/ALPHA/2023",
    "price": 180000,
    "original_price": 180000,
    "image": "assets/placeholder.png",
    "in_stock": true,
    "rating": 4.3,
    "sold_count": 103
  },
  {
    "id": 43,
    "name": "Viên sủi plusszs Multivitamin plus Chanh leo Tuýp 20 viên Alpha",
    "specification": "Tuýp 20 viên",
    "category1": "Thực phẩm chức năng",
    "category2": "Vitamin và khoáng chất",
    "registration_num": "10898/2020/DKSP",
    "price": 50000,
    "original_price": 70000,
    "image": "assets/placeholder.png",
    "in_stock": false,
    "rating": 4.5,
    "sold_count": 105
  },
  {
    "id": 44,
    "name": "Sodermix Hộp 1 tuýp 15g Amazon",
    "specification": "Hộp 1 tuýp 15g",
    "category1": "Trang thiết bị Y tế",
    "category2": "Da Liễu",
    "registration_num": "180000325/PCBA- HN",
    "price": 100000,
    "original_price": 100000,
    "image": "assets/placeholder.png",
    "in_stock": false,
    "rating": 4.5,
    "sold_count": 45
  },
  {
    "id": 45,
    "name": "Dầu gội nhuộm tóc Shitinsof Hán Phương Linh Chi Hộp 3 gói x 15ml",
    "specification": "Hộp 3 gói x 15ml",
    "category1": "Mỹ phẩm",
    "category2": "Chăm sóc cá nhân",
    "registration_num": "14/15/CBMP-HY",
    "price": 60000,
    "original_price": 60000,
    "image": "assets/placeholder.png",
    "in_stock": true,
    "rating": 4.1,
    "sold_count": 11
  },
  {
    "id": 46,
    "name": "Dung dịch vệ sinh phụ Bơ Lá Bàng Nano Bạc chai 200ml An Đại Phát",
    "specification": "chai 200ml",
    "category1": "Mỹ phẩm",
    "category2": "Chăm sóc cá nhân",
    "registration_num": "",
    "price": 190000,
    "original_price": 190000,
    "image": "assets/placeholder.png",
    "in_stock": true,
    "rating": 4.9,
    "sold_count": 59
  },
  {
    "id": 47,
    "name": "Dung dịch vệ sinh cho bé Bơ Trầu Không Nano Bạc Chai 200ml An Đại Phát",
    "specification": "Chai 200ml",
    "category1": "Mỹ phẩm",
    "category2": "Chăm sóc cá nhân",
    "registration_num": "",
    "price": 100000,
    "original_price": 100000,
    "image": "assets/placeholder.png",
    "in_stock": false,
    "rating": 4.0,
    "sold_count": 150
  },
  {
    "id": 48,
    "name": "Bông Gạc Đắp Vết Thương Gói 1 cái An Lành",
    "specification": "6cm x 15cm",
    "category1": "Trang thiết bị Y tế",
    "category2": "Chăm sóc vết thương",
    "registration_num": "TCCS: 13-2022/TCAL",
    "price": 190000,
    "original_price": 190000,
    "image": "assets/placeholder.png",
    "in_stock": true,
    "rating": 4.9,
    "sold_count": 149
  },
  {
    "id": 49,
    "name": "Bút thử thai Mochi Test hộp 1 chiếc An Phú Khang",
    "specification": "Hộp 1 cái",
    "category1": "Trang thiết bị Y tế",
    "category2": "Que Thử/Bút Thử/Test",
    "registration_num": "",
    "price": 180000,
    "original_price": 180000,
    "image": "assets/placeholder.png",
    "in_stock": true,
    "rating": 4.3,
    "sold_count": 43
  },
  {
    "id": 50,
    "name": "Bù điện giải Orezo Sports Tuýp 10 viên sủi Anh Đức",
    "specification": "Tuýp 10 viên",
    "category1": "Thực phẩm chức năng",
    "category2": "Vitamin và khoáng chất",
    "registration_num": "",
    "price": 90000,
    "original_price": 90000,
    "image": "assets/placeholder.png",
    "in_stock": true,
    "rating": 4.4,
    "sold_count": 184
  },
  {
    "id": 51,
    "name": "Aqua MD Hộp 20 ống x 10ml Aqua",
    "specification": "Hộp 20 ống x 10ml",
    "category1": "Thực phẩm chức năng",
    "category2": "Vitamin và khoáng chất",
    "registration_num": "5392/2019/DKSP",
    "price": 190000,
    "original_price": 190000,
    "image": "assets/placeholder.png",
    "in_stock": true,
    "rating": 4.9,
    "sold_count": 69
  },
  {
    "id": 52,
    "name": "Dung dịch sát khuẩn tay nhanh Asirub 500ml",
    "specification": "Chai x 500ml",
    "category1": "Thiết bị y tế",
    "category2": "Chăm sóc cá nhân",
    "registration_num": "VNDP-HC-615-04-12",
    "price": 170000,
    "original_price": 190000,
    "image": "assets/placeholder.png",
    "in_stock": true,
    "rating": 4.2,
    "sold_count": 62
  },
  {
    "id": 53,
    "name": "Viên ngậm Vitamin C hình vịt Lọ 20 viên AUVINA",
    "specification": "Lọ 20 viên",
    "category1": "Thực phẩm chức năng",
    "category2": "Vitamin và khoáng chất",
    "registration_num": "01/2019/0108354357-CBPH",
    "price": 90000,
    "original_price": 90000,
    "image": "assets/placeholder.png",
    "in_stock": true,
    "rating": 4.4,
    "sold_count": 134
  },
  {
    "id": 54,
    "name": "Xịt Khoáng Avene Eau Thermale Spring Water Chai 300ml",
    "specification": "Chai 300ml",
    "category1": "Mỹ phẩm",
    "category2": "Chăm sóc cá nhân",
    "registration_num": "6418953-10131P",
    "price": 120000,
    "original_price": 120000,
    "image": "assets/placeholder.png",
    "in_stock": true,
    "rating": 4.7,
    "sold_count": 77
  },
  {
    "id": 55,
    "name": "Kem bôi chống hăm tã Bepanthen Balm Hộp 1 tuýp x 30g Bayer",
    "specification": "Tuýp 30g",
    "category1": "Mỹ phẩm",
    "category2": "Chăm sóc mẹ và bé",
    "registration_num": "168423/22/CBMP-QLD",
    "price": 190000,
    "original_price": 190000,
    "image": "assets/placeholder.png",
    "in_stock": true,
    "rating": 4.9,
    "sold_count": 149
  },
  {
    "id": 56,
    "name": "Bepanthen Itch Relief Cream tube 20g",
    "specification": "tube 20g",
    "category1": "Mỹ phẩm",
    "category2": "Chăm sóc mẹ và bé",
    "registration_num": "220001681/PCBB-BYT",
    "price": 70000,
    "original_price": 70000,
    "image": "assets/placeholder.png",
    "in_stock": true,
    "rating": 4.2,
    "sold_count": 82
  },
  {
    "id": 57,
    "name": "Bepanthen Balm Hộp 1 tuýp 30g Bayer",
    "specification": "1 tuýp 30g",
    "category1": "Mỹ phẩm",
    "category2": "Chăm sóc mẹ và bé",
    "registration_num": "168423/22/CBMP-QLD",
    "price": 170000,
    "original_price": 190000,
    "image": "assets/placeholder.png",
    "in_stock": true,
    "rating": 4.2,
    "sold_count": 152
  },
  {
    "id": 58,
    "name": "Tẩy tế bào chết môi Lip Scrub almond creme hũ 10,5g",
    "specification": "Hũ",
    "category1": "Mỹ phẩm",
    "category2": "Chăm sóc cá nhân",
    "registration_num": "",
    "price": 70000,
    "original_price": 70000,
    "image": "assets/placeholder.png",
    "in_stock": true,
    "rating": 4.2,
    "sold_count": 142
  },
  {
    "id": 59,
    "name": "Tẩy trang Loreal Micellar Water 3in1 400ml",
    "specification": "chai 400ml",
    "category1": "Mỹ phẩm",
    "category2": "Chăm sóc cá nhân",
    "registration_num": "187045/22/CBMP-QLD",
    "price": 110000,
    "original_price": 130000,
    "image": "assets/placeholder.png",
    "in_stock": true,
    "rating": 4.1,
    "sold_count": 61
  },
  {
    "id": 60,
    "name": "Kẹo Dẻo Zoo Chua Ngọt Hộp 40g Bibica",
    "specification": "Hộp 40g",
    "category1": "Hàng tiêu dùng",
    "category2": "Chăm sóc cá nhân",
    "registration_num": "319/BBC/2021",
    "price": 130000,
    "original_price": 130000,
    "image": "assets/placeholder.png",
    "in_stock": true,
    "rating": 4.3,
    "sold_count": 203
  },
  {
    "id": 61,
    "name": "Nebianax 3% Spray nasale Hộp 1 chai 100ml Biodue",
    "specification": "Hộp 1 chai 100ml",
    "category1": "Thiết bị y tế",
    "category2": "Dụng cụ y tế",
    "registration_num": "210001215/PCBA-HN",
    "price": 180000,
    "original_price": 180000,
    "image": "assets/placeholder.png",
    "in_stock": true,
    "rating": 4.3,
    "sold_count": 173
  },
  {
    "id": 62,
    "name": "Que thử thai Allisa Hộp 1 que Traphaco",
    "specification": "Hộp x 1 que",
    "category1": "Thiết bị y tế",
    "category2": "Que Thử/Bút Thử/Test",
    "registration_num": "220003926/PCBB-HN",
    "price": 60000,
    "original_price": 60000,
    "image": "assets/placeholder.png",
    "in_stock": true,
    "rating": 4.6,
    "sold_count": 86
  },
  {
    "id": 63,
    "name": "Que thử thai HCG Allisa Hộp 1 test Traphaco",
    "specification": "Hộp 1 test",
    "category1": "Thiết bị y tế",
    "category2": "Que Thử/Bút Thử/Test",
    "registration_num": "220003926/PCBB-HN",
    "price": 110000,
    "original_price": 130000,
    "image": "assets/placeholder.png",
    "in_stock": true,
    "rating": 4.6,
    "sold_count": 36
  },
  {
    "id": 64,
    "name": "Cạo lưỡi BQB Vỉ 1 chiếc",
    "specification": "VỈ x 1 chiếc",
    "category1": "Thiết bị y tế",
    "category2": "Chăm sóc cá nhân",
    "registration_num": "",
    "price": 180000,
    "original_price": 180000,
    "image": "assets/placeholder.png",
    "in_stock": true,
    "rating": 4.8,
    "sold_count": 68
  },
  {
    "id": 65,
    "name": "Miếng dán Aikido gel cool patch Hộp 3 gói x 2 miếng Thiên Ân",
    "specification": "Hộp 3 gói x 2 miếng",
    "category1": "Thiết bị y tế",
    "category2": "Chăm sóc mẹ và bé",
    "registration_num": "210000095/PCBA-BN",
    "price": 180000,
    "original_price": 180000,
    "image": "assets/placeholder.png",
    "in_stock": true,
    "rating": 4.3,
    "sold_count": 103
  },
  {
    "id": 66,
    "name": "Cốc nguyệt san Lin Cup comfort fit size 0",
    "specification": "Hộp 1 cốc",
    "category1": "Thiết bị y tế",
    "category2": "Chăm sóc cá nhân",
    "registration_num": "",
    "price": 50000,
    "original_price": 70000,
    "image": "assets/placeholder.png",
    "in_stock": false,
    "rating": 4.5,
    "sold_count": 135
  },
  {
    "id": 67,
    "name": "Muối nở Baking Soda tinh khiết Caster Daily Hộp 1 gói 454g Stherb",
    "specification": "Hộp 1 gói 454g",
    "category1": "Hàng tiêu dùng",
    "category2": "Gia dụng",
    "registration_num": "",
    "price": 180000,
    "original_price": 180000,
    "image": "assets/placeholder.png",
    "in_stock": true,
    "rating": 4.3,
    "sold_count": 153
  },
  {
    "id": 68,
    "name": "Muối nở Baking soda tinh khiết Hộp 454g Casterdaily",
    "specification": "Hộp x 454g",
    "category1": "Hàng tiêu dùng",
    "category2": "Gia dụng",
    "registration_num": "",
    "price": 100000,
    "original_price": 100000,
    "image": "assets/placeholder.png",
    "in_stock": false,
    "rating": 4.5,
    "sold_count": 205
  },
  {
    "id": 69,
    "name": "Xịt mũi họng B-Origanic nano silver Hộp 1 chai 50ml beta care",
    "specification": "Chai 50ml",
    "category1": "Thiết bị y tế",
    "category2": "Chăm Sóc Cá Nhân",
    "registration_num": "200002251/PCBA-HN",
    "price": 180000,
    "original_price": 180000,
    "image": "assets/placeholder.png",
    "in_stock": true,
    "rating": 4.8,
    "sold_count": 138
  },
  {
    "id": 70,
    "name": "DAPYEN Tổ yến thật chưng nấm linh chi Hộp 1 hũ 70ml Đông Á",
    "specification": "Hộp 70ml",
    "category1": "Hàng tiêu dùng",
    "category2": "Chăm sóc cá nhân",
    "registration_num": "01/DAP/2025",
    "price": 80000,
    "original_price": 100000,
    "image": "assets/placeholder.png",
    "in_stock": true,
    "rating": 4.8,
    "sold_count": 68
  },
  {
    "id": 71,
    "name": "Dầu gió Thiên Thảo Trường Sơn Chai x 12ml",
    "specification": "Chai x 12ml",
    "category1": "Thiết bị y tế",
    "category2": "Cao xoa, dầu gió",
    "registration_num": "V1600-H12-10",
    "price": 160000,
    "original_price": 160000,
    "image": "assets/placeholder.png",
    "in_stock": true,
    "rating": 4.6,
    "sold_count": 106
  },
  {
    "id": 72,
    "name": "Dầu khuynh diệp Trường Sơn",
    "specification": "Hộp 1 chai 24ml",
    "category1": "Thiết bị y tế",
    "category2": "Cao xoa, dầu gió",
    "registration_num": "VND-0960-03",
    "price": 140000,
    "original_price": 160000,
    "image": "assets/placeholder.png",
    "in_stock": true,
    "rating": 4.9,
    "sold_count": 29
  },
  {
    "id": 73,
    "name": "Dầu gió Trường Sơn Hộp 1 chai 2,5ml",
    "specification": "chai 2,5ml",
    "category1": "Thiết bị y tế",
    "category2": "Cao xoa, dầu gió",
    "registration_num": "V1600-H12-10",
    "price": 50000,
    "original_price": 70000,
    "image": "assets/placeholder.png",
    "in_stock": false,
    "rating": 4.0,
    "sold_count": 160
  },
  {
    "id": 74,
    "name": "Xịt mũi trẻ em Sterimar Hygiene Baby Hộp 1 chai 50ml Hyphens",
    "specification": "Chai 50ml",
    "category1": "Thiết bị y tế",
    "category2": "Chăm sóc cá nhân",
    "registration_num": "00001777/PCBA-HN",
    "price": 180000,
    "original_price": 180000,
    "image": "assets/placeholder.png",
    "in_stock": true,
    "rating": 4.8,
    "sold_count": 48
  },
  {
    "id": 75,
    "name": "Kem đánh răng dược liệu Thái Dương tuýp 150g",
    "specification": "Tuýp 150g",
    "category1": "Hàng tiêu dùng",
    "category2": "Chăm sóc cá nhân",
    "registration_num": "03/17/CBMP-HN",
    "price": 50000,
    "original_price": 70000,
    "image": "assets/placeholder.png",
    "in_stock": false,
    "rating": 4.5,
    "sold_count": 15
  },
  {
    "id": 76,
    "name": "Nhuộm tóc dược liệu Thái Dương hộp 5 gói màu ĐEN",
    "specification": "Hộp 5 gói x 40g",
    "category1": "Hàng tiêu dùng",
    "category2": "Chăm sóc cá nhân",
    "registration_num": "87191/19/CBMP-QLD",
    "price": 60000,
    "original_price": 60000,
    "image": "assets/placeholder.png",
    "in_stock": true,
    "rating": 4.6,
    "sold_count": 176
  },
  {
    "id": 77,
    "name": "Nhuộm tóc dược liệu Thái Dương Hộp 5 gói 10g",
    "specification": "Hộp 5 gói",
    "category1": "Hàng tiêu dùng",
    "category2": "Chăm sóc cá nhân",
    "registration_num": "87191/19/CBMP-QLD",
    "price": 60000,
    "original_price": 60000,
    "image": "assets/placeholder.png",
    "in_stock": true,
    "rating": 4.6,
    "sold_count": 186
  },
  {
    "id": 78,
    "name": "Kem đánh răng dược liệu Thái Dương Hộp 1 tuýp x 150g",
    "specification": "Tuýp 150g",
    "category1": "Hàng tiêu dùng",
    "category2": "Chăm sóc cá nhân",
    "registration_num": "30/20/CBMP-HNa",
    "price": 120000,
    "original_price": 120000,
    "image": "assets/placeholder.png",
    "in_stock": true,
    "rating": 4.2,
    "sold_count": 112
  },
  {
    "id": 79,
    "name": "Que thử thai HCG Allisa Hộp 1 que thử Traphaco",
    "specification": "Hộp 1 que test",
    "category1": "Trang Thiết Bị Y Tế",
    "category2": "Chăm sóc mẹ và bé",
    "registration_num": "220003926/PCBB-HN",
    "price": 100000,
    "original_price": 100000,
    "image": "assets/placeholder.png",
    "in_stock": false,
    "rating": 4.0,
    "sold_count": 130
  },
  {
    "id": 80,
    "name": "Dung dịch xịt tạo màng sinh học Nacurgo Hộp 1 chai x 12ml Newtech",
    "specification": "Hộp 1 chai x 12ml",
    "category1": "Mỹ Phẩm",
    "category2": "Chăm sóc cá nhân",
    "registration_num": "210000004/PCBA-HN",
    "price": 160000,
    "original_price": 160000,
    "image": "assets/placeholder.png",
    "in_stock": true,
    "rating": 4.6,
    "sold_count": 96
  },
  {
    "id": 81,
    "name": "Kem đánh răng Lipzo 3 tác động Hộp 1 tuýp x 190g Diligo",
    "specification": "Tuýp 190g",
    "category1": "Mỹ Phẩm",
    "category2": "Chăm sóc cá nhân",
    "registration_num": "375/24/CBMP-BN",
    "price": 60000,
    "original_price": 60000,
    "image": "assets/placeholder.png",
    "in_stock": true,
    "rating": 4.6,
    "sold_count": 136
  },
  {
    "id": 82,
    "name": "Kem đánh răng Lipzo dược liệu ngừa chảy máu chân răng Hộp 1 tuýp x 110g Diligo",
    "specification": "Tuýp 110g",
    "category1": "Mỹ Phẩm",
    "category2": "Chăm sóc cá nhân",
    "registration_num": "375/24/CBMP-BN",
    "price": 180000,
    "original_price": 180000,
    "image": "assets/placeholder.png",
    "in_stock": true,
    "rating": 4.8,
    "sold_count": 18
  },
  {
    "id": 83,
    "name": "Kem đánh răng Lipzo Gum Protect Hộp 1 tuýp x 185g Diligo",
    "specification": "Tuýp 185g",
    "category1": "Mỹ Phẩm",
    "category2": "Chăm sóc cá nhân",
    "registration_num": "375/24/CBMP-BN",
    "price": 110000,
    "original_price": 130000,
    "image": "assets/placeholder.png",
    "in_stock": true,
    "rating": 4.1,
    "sold_count": 191
  },
  {
    "id": 84,
    "name": "Xịt lạnh Ligpro cold spray Chai 160ml Quang Thịnh",
    "specification": "Chai 160ml",
    "category1": "Mỹ Phẩm",
    "category2": "Chăm sóc cá nhân",
    "registration_num": "2022/QUANGTHINH",
    "price": 90000,
    "original_price": 90000,
    "image": "assets/placeholder.png",
    "in_stock": true,
    "rating": 4.4,
    "sold_count": 84
  },
  {
    "id": 85,
    "name": "Xịt răng miệng Midkid",
    "specification": "Hộp 1 lọ x 30ml",
    "category1": "Trang Thiết Bị Y Tế",
    "category2": "Chăm sóc cá nhân",
    "registration_num": "220001313/PCBA",
    "price": 190000,
    "original_price": 190000,
    "image": "assets/placeholder.png",
    "in_stock": true,
    "rating": 4.4,
    "sold_count": 54
  },
  {
    "id": 86,
    "name": "Nano bạc pluss Hộp 1 tuýp x 20g Quốc Tế Pháp Âu",
    "specification": "Hộp 1 tuýp 20g",
    "category1": "Mỹ Phẩm",
    "category2": "Chăm sóc cá nhân",
    "registration_num": "17671/23/CBMP-HN",
    "price": 150000,
    "original_price": 150000,
    "image": "assets/placeholder.png",
    "in_stock": false,
    "rating": 4.0,
    "sold_count": 100
  },
  {
    "id": 87,
    "name": "Dung dịch xịt Nacurgo Hộp 1 chai 30ml x 200 lần xịt CVI",
    "specification": "Hộp 1 chai 30ml",
    "category1": "Mỹ Phẩm",
    "category2": "Chăm sóc cá nhân",
    "registration_num": "210000004/PCBA-HN",
    "price": 170000,
    "original_price": 190000,
    "image": "assets/placeholder.png",
    "in_stock": true,
    "rating": 4.7,
    "sold_count": 167
  },
  {
    "id": 88,
    "name": "Dr AC xịt khử mùi 40ml",
    "specification": "lọ 40ml",
    "category1": "Mỹ Phẩm",
    "category2": "Chăm sóc cá nhân",
    "registration_num": "7226/20/CBMP-HN",
    "price": 160000,
    "original_price": 160000,
    "image": "assets/placeholder.png",
    "in_stock": true,
    "rating": 4.6,
    "sold_count": 146
  },
  {
    "id": 89,
    "name": "Xịt Muỗi Thảo Dược Antil-Mos Chai 50ml EcoPhar",
    "specification": "chai 50ml",
    "category1": "Mỹ Phẩm",
    "category2": "Chăm sóc cá nhân",
    "registration_num": "4408/19/CBMP-HN",
    "price": 80000,
    "original_price": 100000,
    "image": "assets/placeholder.png",
    "in_stock": true,
    "rating": 4.3,
    "sold_count": 53
  },
  {
    "id": 90,
    "name": "Nước muối sinh lý Natri clorid 0,9% Chai 500ml Quốc Dân",
    "specification": "chai 500ml",
    "category1": "Trang Thiết Bị Y Tế",
    "category2": "Chăm sóc cá nhân",
    "registration_num": "250002891/PCBB-HN",
    "price": 180000,
    "original_price": 180000,
    "image": "assets/placeholder.png",
    "in_stock": true,
    "rating": 4.3,
    "sold_count": 83
  },
  {
    "id": 91,
    "name": "Nước muối sinh lý Natri clorid 0,9% Chai 1000ml Quốc Dân",
    "specification": "Chai 1000ml",
    "category1": "Trang Thiết Bị Y Tế",
    "category2": "Chăm sóc cá nhân",
    "registration_num": "200000429/PCBA-HN",
    "price": 140000,
    "original_price": 160000,
    "image": "assets/placeholder.png",
    "in_stock": true,
    "rating": 4.4,
    "sold_count": 74
  },
  {
    "id": 92,
    "name": "Nước muối sinh lý Natri clorid 0,9% Lemon Salt Quốc Dân Chai 500ml Elaphe",
    "specification": "Chai 500ml",
    "category1": "Trang Thiết Bị Y Tế",
    "category2": "Chăm sóc cá nhân",
    "registration_num": "TCCS 01:2019/MELP",
    "price": 180000,
    "original_price": 180000,
    "image": "assets/placeholder.png",
    "in_stock": true,
    "rating": 4.3,
    "sold_count": 173
  },
  {
    "id": 93,
    "name": "Agiclovir 400mg Hộp 3 vỉ x 10 viên Agimexpharm",
    "specification": "hộp 3 vỉ x 10 viên",
    "category1": "Kháng Virus",
    "category2": "Kháng Virus",
    "registration_num": "893110204800",
    "price": 80000,
    "original_price": 100000,
    "image": "assets/placeholder.png",
    "in_stock": true,
    "rating": 4.8,
    "sold_count": 118
  },
  {
    "id": 94,
    "name": "Agiclovir 800mg Hộp 10 vỉ x 10 viên Agimexpharm",
    "specification": "Hộp 10 vỉ x 10 viên",
    "category1": "Kháng Virus",
    "category2": "Kháng Virus",
    "registration_num": "893110255023",
    "price": 130000,
    "original_price": 130000,
    "image": "assets/placeholder.png",
    "in_stock": true,
    "rating": 4.3,
    "sold_count": 13
  },
  {
    "id": 95,
    "name": "Kem đánh răng trẻ em Bubukids hương dâu Hộp 1 tuýp 75g Abipha",
    "specification": "Hộp 1 tuýp 75g",
    "category1": "Trang Thiết Bị Y Tế",
    "category2": "Chăm sóc cá nhân",
    "registration_num": "20196/24/CBMP-HN",
    "price": 190000,
    "original_price": 190000,
    "image": "assets/placeholder.png",
    "in_stock": true,
    "rating": 4.4,
    "sold_count": 84
  },
  {
    "id": 96,
    "name": "Koras Đại tràng plus Hộp 20 gói 10ml Hợp Nhất",
    "specification": "Hộp 20 gói",
    "category1": "Thực Phẩm Chức Năng",
    "category2": "Tiêu hóa Gan Mật",
    "registration_num": "4138/2023/ĐKSP",
    "price": 170000,
    "original_price": 190000,
    "image": "assets/placeholder.png",
    "in_stock": true,
    "rating": 4.2,
    "sold_count": 102
  },
  {
    "id": 97,
    "name": "Koras Bổ Thần Kinh Hộp 3 vỉ x 10 viên Hợp Nhất",
    "specification": "Hộp 3 vỉ x 10 viên",
    "category1": "Thực Phẩm Chức Năng",
    "category2": "Thần kinh",
    "registration_num": "5001/2023/ĐKSP",
    "price": 190000,
    "original_price": 190000,
    "image": "assets/placeholder.png",
    "in_stock": true,
    "rating": 4.9,
    "sold_count": 99
  },
  {
    "id": 98,
    "name": "Entergolzinc 2 tỷ bào tử hộp 4 vỉ x 5 ống (cam)",
    "specification": "hộp 4 vỉ x 5 ống",
    "category1": "Thực Phẩm Chức Năng",
    "category2": "Tiêu hóa Gan Mật",
    "registration_num": "5442/2020/ĐKSP",
    "price": 140000,
    "original_price": 160000,
    "image": "assets/placeholder.png",
    "in_stock": true,
    "rating": 4.4,
    "sold_count": 64
  },
  {
    "id": 99,
    "name": "Entergolzinc 2 tỷ bào tử hộp 4 vỉ x 5 ống (xanh)",
    "specification": "hộp 4 vỉ x 5 ống",
    "category1": "Thực Phẩm Chức Năng",
    "category2": "Tiêu hóa Gan Mật",
    "registration_num": "5442/2020/ĐKSP",
    "price": 160000,
    "original_price": 160000,
    "image": "assets/placeholder.png",
    "in_stock": true,
    "rating": 4.1,
    "sold_count": 11
  },
  {
    "id": 100,
    "name": "Bổ thần kinh TW Extra Hộp 3 vỉ x 10 viên Akopha Pháp",
    "specification": "Hộp 3 vỉ x 10 viên",
    "category1": "Thực Phẩm Chức Năng",
    "category2": "Thần kinh",
    "registration_num": "3467/2023/ĐKSP",
    "price": 90000,
    "original_price": 90000,
    "image": "assets/placeholder.png",
    "in_stock": true,
    "rating": 4.9,
    "sold_count": 209
  },
  {
    "id": 101,
    "name": "Viên xương khớp Joint Flex Hộp 1 lọ 60 viên EcoPhar",
    "specification": "Hộp 1 lọ x 60 viên",
    "category1": "Thực Phẩm Chức Năng",
    "category2": "Cơ Xương Khớp",
    "registration_num": "8222/2018/ĐKSP",
    "price": 100000,
    "original_price": 100000,
    "image": "assets/placeholder.png",
    "in_stock": false,
    "rating": 4.5,
    "sold_count": 105
  },
  {
    "id": 102,
    "name": "Viên bổ phế Hofever Hộp 3 vỉ x 10 viên Gold care",
    "specification": "Hộp 3 vỉ x 10 viên",
    "category1": "Thực Phẩm Chức Năng",
    "category2": "Hô hấp",
    "registration_num": "6443/2021/ĐKSP",
    "price": 180000,
    "original_price": 180000,
    "image": "assets/placeholder.png",
    "in_stock": true,
    "rating": 4.3,
    "sold_count": 163
  },
  {
    "id": 103,
    "name": "Hoạt huyết dưỡng não Brain Extra Hộp 10 vỉ x 10 viên nang mềm Mary's",
    "specification": "Hộp 10 vỉ x 10 viên nang mềm",
    "category1": "Thực Phẩm Chức Năng",
    "category2": "Thần kinh",
    "registration_num": "1567/2023/ĐKSP",
    "price": 120000,
    "original_price": 120000,
    "image": "assets/placeholder.png",
    "in_stock": true,
    "rating": 4.7,
    "sold_count": 37
  },
  {
    "id": 104,
    "name": "Nước tắm gội thảo dược Dr.Papie 0-3 tuổi Hộp 1 chai 230ml Starmed",
    "specification": "Hộp 1 chai x 230ml",
    "category1": "Mỹ Phẩm",
    "category2": "Chăm sóc cá nhân",
    "registration_num": "02/22/CBMP-HY",
    "price": 60000,
    "original_price": 60000,
    "image": "assets/placeholder.png",
    "in_stock": true,
    "rating": 4.1,
    "sold_count": 111
  },
  {
    "id": 105,
    "name": "Gạc răng miệng Dr.Papie 0+ Hộp 30 gói Starmed",
    "specification": "Hộp 30 gói",
    "category1": "Trang Thiết Bị Y Tế",
    "category2": "Chăm sóc cá nhân",
    "registration_num": "210002052/PCBA-HN",
    "price": 70000,
    "original_price": 70000,
    "image": "assets/placeholder.png",
    "in_stock": true,
    "rating": 4.7,
    "sold_count": 177
  },
  {
    "id": 106,
    "name": "Khăn hạ sốt Dr.Papie 0+ Hộp 5 túi x 5 khăn Starmed",
    "specification": "Hộp 5 túi x 5 khăn",
    "category1": "Trang Thiết Bị Y Tế",
    "category2": "Giảm đau Hạ sốt",
    "registration_num": "210002055/PCBA-HN",
    "price": 90000,
    "original_price": 90000,
    "image": "assets/placeholder.png",
    "in_stock": true,
    "rating": 4.9,
    "sold_count": 139
  },
  {
    "id": 107,
    "name": "Khăn hạ sốt Dr.Papie 3+ Hộp 5 gói Starmed",
    "specification": "Hộp 5 gói",
    "category1": "Trang Thiết Bị Y Tế",
    "category2": "Giảm đau Hạ sốt",
    "registration_num": "1900000504/PCBA-HN",
    "price": 50000,
    "original_price": 70000,
    "image": "assets/placeholder.png",
    "in_stock": false,
    "rating": 4.5,
    "sold_count": 175
  },
  {
    "id": 108,
    "name": "Profen 100mg/10ml Hộp 2 vỉ x 5 ống hỗn dịch uống CPC1",
    "specification": "Hộp 2 vỉ x 5 ống",
    "category1": "Thuốc Không Kê Đơn",
    "category2": "Giảm đau Hạ sốt",
    "registration_num": "893100346024",
    "price": 130000,
    "original_price": 130000,
    "image": "assets/placeholder.png",
    "in_stock": true,
    "rating": 4.3,
    "sold_count": 33
  },
  {
    "id": 109,
    "name": "Dung dịch nhỏ tai Fosmitic Hộp 1 chai 5ml CPC1",
    "specification": "Chai 5ml",
    "category1": "Thuốc Kê Đơn",
    "category2": "Hô hấp",
    "registration_num": "VD-33152-19",
    "price": 160000,
    "original_price": 160000,
    "image": "assets/placeholder.png",
    "in_stock": true,
    "rating": 4.6,
    "sold_count": 26
  },
  {
    "id": 110,
    "name": "Zensalbu Nebulet 2,5mg Hộp 2 vỉ x 5 ống CPC1",
    "specification": "Hộp 2 Vỉ x 5 Ống",
    "category1": "Thuốc Kê Đơn",
    "category2": "Hô hấp",
    "registration_num": "893115019000",
    "price": 130000,
    "original_price": 130000,
    "image": "assets/placeholder.png",
    "in_stock": true,
    "rating": 4.8,
    "sold_count": 168
  },
  {
    "id": 111,
    "name": "Oralegic 30mg/5ml Hộp 2 vỉ x 5 ống CPC1",
    "specification": "Hộp 2 Vỉ x 5 Ống X 5ml",
    "category1": "Thuốc Không Kê Đơn",
    "category2": "Dị ứng và Miễn dịch",
    "registration_num": "893100880624",
    "price": 150000,
    "original_price": 150000,
    "image": "assets/placeholder.png",
    "in_stock": false,
    "rating": 4.5,
    "sold_count": 15
  },
  {
    "id": 112,
    "name": "Novoteeth Hộp 1 tuýp 10g CPC1",
    "specification": "Hộp 1 tuýp 10g",
    "category1": "Trang Thiết Bị Y Tế",
    "category2": "Chăm sóc cá nhân",
    "registration_num": "190000853/PCBA-HN",
    "price": 60000,
    "original_price": 60000,
    "image": "assets/placeholder.png",
    "in_stock": true,
    "rating": 4.6,
    "sold_count": 36
  },
  {
    "id": 113,
    "name": "Novocough Hộp 20 ống x 5ml CPC1",
    "specification": "Hộp 20 Ống X 5ml",
    "category1": "Thuốc Kê Đơn",
    "category2": "Hô hấp",
    "registration_num": "893110880524",
    "price": 130000,
    "original_price": 130000,
    "image": "assets/placeholder.png",
    "in_stock": true,
    "rating": 4.8,
    "sold_count": 178
  },
  {
    "id": 114,
    "name": "Metagin Hộp 2 vỉ x 6 viên đặt âm đạo CPC1",
    "specification": "Hộp 2 vỉ x 6 viên",
    "category1": "Thuốc Kê Đơn",
    "category2": "Nội tiết và Sinh lý",
    "registration_num": "220000654/PCBB-HN",
    "price": 70000,
    "original_price": 70000,
    "image": "assets/placeholder.png",
    "in_stock": true,
    "rating": 4.7,
    "sold_count": 127
  },
  {
    "id": 115,
    "name": "Guacanyl Hộp 4 vỉ x 5 ống CPC1",
    "specification": "Hộp 4 Vỉ x 5 Ống",
    "category1": "Thuốc Kê Đơn",
    "category2": "Hô hấp",
    "registration_num": "893110281523",
    "price": 60000,
    "original_price": 60000,
    "image": "assets/placeholder.png",
    "in_stock": true,
    "rating": 4.1,
    "sold_count": 201
  },
  {
    "id": 116,
    "name": "Inflagic Hộp 2 vỉ x 5 ống CPC1",
    "specification": "Hộp 10 ống x 5ml, Hộp 20 ống x 5ml, Hộp 30 ống x 5ml, Hộp 40 ống x 5ml",
    "category1": "Thuốc Kê Đơn",
    "category2": "Hô hấp",
    "registration_num": "893110280300",
    "price": 90000,
    "original_price": 90000,
    "image": "assets/placeholder.png",
    "in_stock": true,
    "rating": 4.9,
    "sold_count": 19
  },
  {
    "id": 117,
    "name": "Falgankid 25mg/ml Hộp 4 vỉ x 5 ống CPC1",
    "specification": "Hộp 4 Vỉ x 5 Ống",
    "category1": "Thuốc Không Kê Đơn",
    "category2": "Giảm đau Hạ sốt",
    "registration_num": "893100277700",
    "price": 180000,
    "original_price": 180000,
    "image": "assets/placeholder.png",
    "in_stock": true,
    "rating": 4.3,
    "sold_count": 123
  },
  {
    "id": 118,
    "name": "Falgankid 160mg/10ml Hộp 4 vỉ x 5 ống CPC1",
    "specification": "Hộp 4 Vỉ x 5 Ống",
    "category1": "Thuốc Không Kê Đơn",
    "category2": "Giảm đau Hạ sốt",
    "registration_num": "893100318000",
    "price": 50000,
    "original_price": 70000,
    "image": "assets/placeholder.png",
    "in_stock": false,
    "rating": 4.5,
    "sold_count": 95
  },
  {
    "id": 119,
    "name": "Dung dịch Novolinda Hộp 1 chai 30ml CPC1",
    "specification": "Hộp x 30ml",
    "category1": "Thuốc Kê Đơn",
    "category2": "Da liễu",
    "registration_num": "893110204624",
    "price": 140000,
    "original_price": 160000,
    "image": "assets/placeholder.png",
    "in_stock": true,
    "rating": 4.4,
    "sold_count": 44
  },
  {
    "id": 120,
    "name": "Dung dịch nhỏ mắt Ketofen-Drop 0,5mg/ml Hộp 1 chai 5ml CPC1HN",
    "specification": "Chai 5ml",
    "category1": "Thuốc Kê Đơn",
    "category2": "Mắt",
    "registration_num": "893110880124",
    "price": 70000,
    "original_price": 70000,
    "image": "assets/placeholder.png",
    "in_stock": true,
    "rating": 4.2,
    "sold_count": 102
  },
  {
    "id": 121,
    "name": "Novocough 6mg/ml Hộp 20 ống x 5ml dung dịch uống CPC1",
    "specification": "Hộp 20 ống",
    "category1": "Thuốc Kê Đơn",
    "category2": "Hô hấp",
    "registration_num": "893110880524",
    "price": 110000,
    "original_price": 130000,
    "image": "assets/placeholder.png",
    "in_stock": true,
    "rating": 4.1,
    "sold_count": 41
  },
  {
    "id": 122,
    "name": "Fogyma 50mg/10ml Hộp 4 vỉ x 5 ống CPC1",
    "specification": "Hộp 20 ống",
    "category1": "Thuốc Không Kê Đơn",
    "category2": "Vitamin và khoáng chất",
    "registration_num": "893100105624",
    "price": 110000,
    "original_price": 130000,
    "image": "assets/placeholder.png",
    "in_stock": true,
    "rating": 4.1,
    "sold_count": 21
  },
  {
    "id": 123,
    "name": "Freeskin Bọt rửa mặt ngừa mụn Cleansing Foam Hộp 1 chai x 120ml Novocare",
    "specification": "Chai 120ml",
    "category1": "Trang Thiết Bị Y Tế",
    "category2": "Chăm sóc cá nhân",
    "registration_num": "82/24/CBMP-HNa",
    "price": 140000,
    "original_price": 160000,
    "image": "assets/placeholder.png",
    "in_stock": true,
    "rating": 4.9,
    "sold_count": 169
  },
  {
    "id": 124,
    "name": "Freeskin forte Xịt ngừa mụn ngoài da Acne Clear Hộp 1 chai x 80ml Novocare",
    "specification": "Chai 80ml",
    "category1": "Trang Thiết Bị Y Tế",
    "category2": "Chăm sóc cá nhân",
    "registration_num": "240000038/PCBA-HNa",
    "price": 160000,
    "original_price": 160000,
    "image": "assets/placeholder.png",
    "in_stock": true,
    "rating": 4.6,
    "sold_count": 166
  },
  {
    "id": 125,
    "name": "Dexalevo Drop Hộp 1 lọ x 5ml CPC1HN",
    "specification": "Hộp 1 lọ x 5ml",
    "category1": "Thuốc Kê Đơn",
    "category2": "Mắt",
    "registration_num": "893115204024",
    "price": 80000,
    "original_price": 100000,
    "image": "assets/placeholder.png",
    "in_stock": true,
    "rating": 4.8,
    "sold_count": 38
  },
  {
    "id": 126,
    "name": "Oralegic 60mg/10ml Hộp 2 Vỉ 5 ống 10ml CPC1",
    "specification": "Hộp 2 Vỉ 5 ống 10ml",
    "category1": "Thuốc Không Kê Đơn",
    "category2": "Dị ứng và Miễn dịch",
    "registration_num": "893100880624",
    "price": 130000,
    "original_price": 130000,
    "image": "assets/placeholder.png",
    "in_stock": true,
    "rating": 4.8,
    "sold_count": 158
  },
  {
    "id": 127,
    "name": "Dung dịch uống Novocough 6mg/ml hộp 20 ống x 5ml CPC1HN",
    "specification": "hộp 20 ống x 5ml",
    "category1": "Thuốc Kê Đơn",
    "category2": "Hô hấp",
    "registration_num": "893110880524",
    "price": 90000,
    "original_price": 90000,
    "image": "assets/placeholder.png",
    "in_stock": true,
    "rating": 4.4,
    "sold_count": 74
  },
  {
    "id": 128,
    "name": "Zensalbu 2.5/2,5ml Hộp 2 vỉ x 5 ống CPC1",
    "specification": "Hộp 2 vỉ x 5 ống CPC1",
    "category1": "Thuốc Kê Đơn",
    "category2": "Hô hấp",
    "registration_num": "893115019000",
    "price": 70000,
    "original_price": 70000,
    "image": "assets/placeholder.png",
    "in_stock": true,
    "rating": 4.2,
    "sold_count": 152
  },
  {
    "id": 129,
    "name": "Falgankid 80mg/5ml Hộp 4 vỉ x 5 ống 5ml CPC1",
    "specification": "Hộp 4 vỉ x 5 ống",
    "category1": "Thuốc Không Kê Đơn",
    "category2": "Giảm đau Hạ sốt",
    "registration_num": "VD-21506-14",
    "price": 150000,
    "original_price": 150000,
    "image": "assets/placeholder.png",
    "in_stock": false,
    "rating": 4.0,
    "sold_count": 70
  },
  {
    "id": 130,
    "name": "Eucol 1,25mg/5ml Hộp 4 vỉ x 5 ống CPC1",
    "specification": "Hộp 4 vỉ x 5 ống",
    "category1": "Thuốc Không Kê Đơn",
    "category2": "Hô hấp",
    "registration_num": "893100220924",
    "price": 60000,
    "original_price": 60000,
    "image": "assets/placeholder.png",
    "in_stock": true,
    "rating": 4.6,
    "sold_count": 196
  },
  {
    "id": 131,
    "name": "Falgankid 25mg/ml Hộp 4 vỉ x 5 ống 10ml CPC1",
    "specification": "Hộp 4 vỉ x 5 ống nhựa x 10ml",
    "category1": "Thuốc Không Kê Đơn",
    "category2": "Giảm đau Hạ sốt",
    "registration_num": "893100277700",
    "price": 100000,
    "original_price": 100000,
    "image": "assets/placeholder.png",
    "in_stock": false,
    "rating": 4.0,
    "sold_count": 90
  },
  {
    "id": 132,
    "name": "Falgankid 16mg/ml Hộp 4 vỉ x 5 ống 10ml CPC1",
    "specification": "Hộp 4 vỉ x 5 ống nhựa x 10ml",
    "category1": "Thuốc Không Kê Đơn",
    "category2": "Giảm đau Hạ sốt",
    "registration_num": "893100318000",
    "price": 120000,
    "original_price": 120000,
    "image": "assets/placeholder.png",
    "in_stock": true,
    "rating": 4.7,
    "sold_count": 147
  },
  {
    "id": 133,
    "name": "Pabemin 325 Hộp 30 gói x 2,5g thuốc cốm DCL",
    "specification": "Hộp 30 gói x 2,5g thuốc cốm",
    "category1": "Thuốc Không Kê Đơn",
    "category2": "Giảm đau Hạ sốt",
    "registration_num": "893100067900",
    "price": 100000,
    "original_price": 100000,
    "image": "assets/placeholder.png",
    "in_stock": false,
    "rating": 4.5,
    "sold_count": 95
  },
  {
    "id": 134,
    "name": "Vitamin PP 50 Hộp 1 lọ 60 viên nén Pharmedic",
    "specification": "Lọ 60 viên",
    "category1": "Thuốc Không Kê Đơn",
    "category2": "Vitamin và khoáng chất",
    "registration_num": "VD-22831-15",
    "price": 190000,
    "original_price": 190000,
    "image": "assets/placeholder.png",
    "in_stock": true,
    "rating": 4.4,
    "sold_count": 144
  },
  {
    "id": 135,
    "name": "Dung dịch vệ sinh Gynofar Chai 500ml Pharmedic",
    "specification": "Chai 500ml",
    "category1": "Mỹ Phẩm",
    "category2": "Nội tiết và Sinh lý",
    "registration_num": "176/22/CBMP-HCM",
    "price": 120000,
    "original_price": 120000,
    "image": "assets/placeholder.png",
    "in_stock": true,
    "rating": 4.2,
    "sold_count": 132
  },
  {
    "id": 136,
    "name": "Dung dịch vệ sinh Gynofar Chai 250ml Pharmedic",
    "specification": "Chai 250ml",
    "category1": "Mỹ Phẩm",
    "category2": "Nội tiết và Sinh lý",
    "registration_num": "176/22/CBMP-HCM",
    "price": 190000,
    "original_price": 190000,
    "image": "assets/placeholder.png",
    "in_stock": true,
    "rating": 4.9,
    "sold_count": 159
  },
  {
    "id": 137,
    "name": "Viên Dưỡng Khớp Davimax Flex Hộp 1 chai 60 viên Davico",
    "specification": "Hộp 1 chai 60 viên",
    "category1": "Thực Phẩm Chức Năng",
    "category2": "Cơ Xương Khớp",
    "registration_num": "5381/2018/ĐKSP",
    "price": 100000,
    "original_price": 100000,
    "image": "assets/placeholder.png",
    "in_stock": false,
    "rating": 4.5,
    "sold_count": 45
  },
  {
    "id": 138,
    "name": "Sugar Betnadavi Hộp 1 lọ x 30 viên DavicoPharma",
    "specification": "Hộp 1 lọ x 30 viên",
    "category1": "Thực Phẩm Chức Năng",
    "category2": "Tim mạch Huyết áp",
    "registration_num": "",
    "price": 150000,
    "original_price": 150000,
    "image": "assets/placeholder.png",
    "in_stock": false,
    "rating": 4.0,
    "sold_count": 70
  },
  {
    "id": 139,
    "name": "Trà râu ngô rau má Hộp 150gr Á Châu",
    "specification": "Hộp 150gr",
    "category1": "Thực Phẩm Chức Năng",
    "category2": "Tiêu hóa Gan Mật",
    "registration_num": "07/ĐY/2019-CBPH",
    "price": 140000,
    "original_price": 160000,
    "image": "assets/placeholder.png",
    "in_stock": true,
    "rating": 4.4,
    "sold_count": 194
  },
  {
    "id": 140,
    "name": "Vitamin C 50mg lọ 100 viên Đại uy",
    "specification": "Chai 100 viên",
    "category1": "Thực Phẩm Chức Năng",
    "category2": "Vitamin và khoáng chất",
    "registration_num": "10/ĐY/2020-CBPH",
    "price": 90000,
    "original_price": 90000,
    "image": "assets/placeholder.png",
    "in_stock": true,
    "rating": 4.4,
    "sold_count": 154
  },
  {
    "id": 141,
    "name": "Promethazin 2% Hộp 1 tuýp 10g Medipharco",
    "specification": "Hộp 1 Tuýp x 10g",
    "category1": "Dị ứng và Miễn dịch",
    "category2": "Da liễu",
    "registration_num": "893100203300",
    "price": 80000,
    "original_price": 100000,
    "image": "assets/placeholder.png",
    "in_stock": true,
    "rating": 4.3,
    "sold_count": 53
  },
  {
    "id": 142,
    "name": "Que thử thai HCG Goldentime Hộp 1 test",
    "specification": "Hộp 1 test",
    "category1": "Trang thiết bị Y tế",
    "category2": "Chăm sóc cá nhân",
    "registration_num": "",
    "price": 190000,
    "original_price": 190000,
    "image": "assets/placeholder.png",
    "in_stock": true,
    "rating": 4.9,
    "sold_count": 119
  },
  {
    "id": 143,
    "name": "Xịt xua đuổi muỗi Zika chai 100ml Tinh dầu xứ Huế",
    "specification": "chai 100ml",
    "category1": "Trang thiết bị Y tế",
    "category2": "Chăm Sóc Cá Nhân",
    "registration_num": "",
    "price": 130000,
    "original_price": 130000,
    "image": "assets/placeholder.png",
    "in_stock": true,
    "rating": 4.3,
    "sold_count": 133
  },
  {
    "id": 144,
    "name": "Gạc y tế tiệt trùng 3 con nai Gói 10 miếng 5 x 6cm x 8 lớp Đông Fa",
    "specification": "Gói 10 miếng",
    "category1": "Trang thiết bị Y tế",
    "category2": "Chăm Sóc Vết Thương",
    "registration_num": "",
    "price": 50000,
    "original_price": 70000,
    "image": "assets/placeholder.png",
    "in_stock": false,
    "rating": 4.5,
    "sold_count": 135
  },
  {
    "id": 145,
    "name": "Test cúm A-B Hộp 25 bộ Lyher",
    "specification": "Hộp 25 bộ",
    "category1": "Trang thiết bị Y tế",
    "category2": "Que Thử/Bút Thử/Test",
    "registration_num": "",
    "price": 100000,
    "original_price": 100000,
    "image": "assets/placeholder.png",
    "in_stock": false,
    "rating": 4.5,
    "sold_count": 45
  },
  {
    "id": 146,
    "name": "Nhiệt kế điện tử Truelife Hộp 1 chiếc Hangzhou",
    "specification": "Hộp 1 chiếc",
    "category1": "Trang thiết bị Y tế",
    "category2": "Máy Móc Và Thiết Bị Đo",
    "registration_num": "",
    "price": 180000,
    "original_price": 180000,
    "image": "assets/placeholder.png",
    "in_stock": true,
    "rating": 4.8,
    "sold_count": 118
  },
  {
    "id": 147,
    "name": "Băng dính vết thương vô trùng 6cm x 7cm Happy patch Hộp 25 cái",
    "specification": "Hộp 25 cái",
    "category1": "Trang thiết bị Y tế",
    "category2": "Dụng cụ sơ cứu",
    "registration_num": "",
    "price": 100000,
    "original_price": 100000,
    "image": "assets/placeholder.png",
    "in_stock": false,
    "rating": 4.0,
    "sold_count": 180
  },
  {
    "id": 148,
    "name": "Que thử ma túy 4 chân DRUGS OF ABUSE TEST (VISTA) hộp 1 cái",
    "specification": "Hộp x 1 cái",
    "category1": "Hàng thiết bị y tế",
    "category2": "Chẩn đoán xét nghiệm",
    "registration_num": "210001234/PCBA-HN",
    "price": 170000,
    "original_price": 190000,
    "image": "assets/placeholder.png",
    "in_stock": true,
    "rating": 4.2,
    "sold_count": 122
  },
  {
    "id": 149,
    "name": "Khẩu trang y tế Sky màu đen Hộp 50 cái Nguyễn Gia",
    "specification": "Hộp 5 gói x 10 chiếc",
    "category1": "Hàng thiết bị y tế",
    "category2": "Vật tư bảo hộ",
    "registration_num": "210001567/PCBA-HCM",
    "price": 180000,
    "original_price": 180000,
    "image": "assets/placeholder.png",
    "in_stock": true,
    "rating": 4.3,
    "sold_count": 33
  },
  {
    "id": 150,
    "name": "Khẩu trang y tế Sky 4 lớp Hộp 5 gói x 10 cái Nguyễn Gia",
    "specification": "Hộp 5 gói x 10 cái",
    "category1": "Hàng thiết bị y tế",
    "category2": "Vật tư bảo hộ",
    "registration_num": "210001568/PCBA-HCM",
    "price": 130000,
    "original_price": 130000,
    "image": "assets/placeholder.png",
    "in_stock": true,
    "rating": 4.8,
    "sold_count": 208
  },
  {
    "id": 151,
    "name": "Tiêu khiết thanh Hộp 3 vỉ x 10 viên Y Dược quốc tế",
    "specification": "Hộp 3 vỉ x 10 viên",
    "category1": "Thuốc đông dược",
    "category2": "Tai mũi họng",
    "registration_num": "V251-H12-10",
    "price": 90000,
    "original_price": 90000,
    "image": "assets/placeholder.png",
    "in_stock": true,
    "rating": 4.4,
    "sold_count": 74
  },
  {
    "id": 152,
    "name": "Dung dịch vệ sinh mũi Zenko chai 75ml Nhất Nhất",
    "specification": "Hộp 1 chai 75ml",
    "category1": "Hàng thiết bị y tế",
    "category2": "Tai mũi họng",
    "registration_num": "220000221/PCBA-HN",
    "price": 180000,
    "original_price": 180000,
    "image": "assets/placeholder.png",
    "in_stock": true,
    "rating": 4.8,
    "sold_count": 58
  },
  {
    "id": 153,
    "name": "Nhiệt kế điện tử Sika MT-811 HMP",
    "specification": "Hộp 1 cái",
    "category1": "Hàng thiết bị y tế",
    "category2": "Thiết bị đo thân nhiệt",
    "registration_num": "200001111/PCBA-HN",
    "price": 50000,
    "original_price": 70000,
    "image": "assets/placeholder.png",
    "in_stock": false,
    "rating": 4.5,
    "sold_count": 85
  },
  {
    "id": 154,
    "name": "Nhiệt kế điện tử Sika ECT-2A/B HMP",
    "specification": "Hộp 1 cái",
    "category1": "Hàng thiết bị y tế",
    "category2": "Thiết bị đo thân nhiệt",
    "registration_num": "200001112/PCBA-HN",
    "price": 110000,
    "original_price": 130000,
    "image": "assets/placeholder.png",
    "in_stock": true,
    "rating": 4.1,
    "sold_count": 101
  },
  {
    "id": 155,
    "name": "Nhiệt kế điện tử Sika Hộp 1 chiếc Ningbo",
    "specification": "Hộp 1 chiếc",
    "category1": "Hàng thiết bị y tế",
    "category2": "Thiết bị đo thân nhiệt",
    "registration_num": "200001113/PCBA-HN",
    "price": 180000,
    "original_price": 180000,
    "image": "assets/placeholder.png",
    "in_stock": true,
    "rating": 4.8,
    "sold_count": 118
  },
  {
    "id": 156,
    "name": "Xịt mũi người lớn Otosan Nasal Spray Forte 30ml",
    "specification": "Chai 30ml",
    "category1": "Trang thiết bị y tế",
    "category2": "Hô hấp",
    "registration_num": "220000221/PCBA-HN",
    "price": 50000,
    "original_price": 70000,
    "image": "assets/placeholder.png",
    "in_stock": false,
    "rating": 4.0,
    "sold_count": 30
  },
  {
    "id": 157,
    "name": "Muối rửa mũi xoang Otosan Nasal Wash Hộp 30 Gói",
    "specification": "Hộp 30 Gói",
    "category1": "Trang thiết bị y tế",
    "category2": "Hô hấp",
    "registration_num": "220000219/PCBA-HN",
    "price": 130000,
    "original_price": 130000,
    "image": "assets/placeholder.png",
    "in_stock": true,
    "rating": 4.8,
    "sold_count": 78
  },
  {
    "id": 158,
    "name": "Khẩu trang y tế Palmy Hộp 50 cái",
    "specification": "Hộp 50 cái",
    "category1": "Hàng thiết bị y tế",
    "category2": "Vật tư y tế",
    "registration_num": "210001546/PCBA-HN",
    "price": 70000,
    "original_price": 70000,
    "image": "assets/placeholder.png",
    "in_stock": true,
    "rating": 4.7,
    "sold_count": 167
  },
  {
    "id": 159,
    "name": "Bông Tròn SoftTip Gói 40g Phú Gia",
    "specification": "Gói 40g",
    "category1": "Hàng thiết bị y tế",
    "category2": "Vật tư y tế",
    "registration_num": "210001247/PCBA-HN",
    "price": 170000,
    "original_price": 190000,
    "image": "assets/placeholder.png",
    "in_stock": true,
    "rating": 4.2,
    "sold_count": 202
  },
  {
    "id": 160,
    "name": "Muối rửa mũi NasalRinse Hộp 25 gói x 3.75g Provix",
    "specification": "Hộp 20 gói",
    "category1": "Trang thiết bị y tế",
    "category2": "Hô hấp",
    "registration_num": "210001189/PCBA-HCM",
    "price": 140000,
    "original_price": 160000,
    "image": "assets/placeholder.png",
    "in_stock": true,
    "rating": 4.9,
    "sold_count": 39
  },
  {
    "id": 161,
    "name": "Băng chun y tế 3 inch ( 2 móc ) Hộp 12 chiếc Quang Mậu",
    "specification": "Hộp 12 chiếc",
    "category1": "Trang thiết bị y tế",
    "category2": "Chăm sóc vết thương",
    "registration_num": "",
    "price": 50000,
    "original_price": 70000,
    "image": "assets/placeholder.png",
    "in_stock": false,
    "rating": 4.0,
    "sold_count": 170
  },
  {
    "id": 162,
    "name": "Gạc vệ sinh răng miệng Dr.Baby Hộp 30 gói Quang Xanh",
    "specification": "Hộp 30 gói",
    "category1": "Trang thiết bị y tế",
    "category2": "Chăm sóc mẹ và bé",
    "registration_num": "",
    "price": 90000,
    "original_price": 90000,
    "image": "assets/placeholder.png",
    "in_stock": true,
    "rating": 4.4,
    "sold_count": 194
  },
  {
    "id": 163,
    "name": "Gel bôi trơn Durex K-Y Jelly Tuýp 50g Reckitt",
    "specification": "Hộp 1 Chai x 50g",
    "category1": "Trang thiết bị y tế",
    "category2": "Nói tiết và Sinh lý",
    "registration_num": "230000717/PCBB-HCM",
    "price": 130000,
    "original_price": 130000,
    "image": "assets/placeholder.png",
    "in_stock": true,
    "rating": 4.8,
    "sold_count": 48
  },
  {
    "id": 164,
    "name": "Gel bôi trơn Durex play Classic gói 5ml",
    "specification": "Gói 5ml",
    "category1": "Trang thiết bị y tế",
    "category2": "Chăm sóc cá nhân",
    "registration_num": "230000717/PCBB-HCM",
    "price": 190000,
    "original_price": 190000,
    "image": "assets/placeholder.png",
    "in_stock": true,
    "rating": 4.4,
    "sold_count": 174
  },
  {
    "id": 165,
    "name": "Gel bôi trơn Durex K-Y Jelly Hộp 1 tuýp x 50g",
    "specification": "Tuýp 50g",
    "category1": "Trang thiết bị y tế",
    "category2": "Nói tiết và Sinh lý",
    "registration_num": "230000717/PCBB-HCM",
    "price": 190000,
    "original_price": 190000,
    "image": "assets/placeholder.png",
    "in_stock": true,
    "rating": 4.9,
    "sold_count": 209
  },
  {
    "id": 166,
    "name": "Gel bôi trơn Durex K-Y Jelly Hộp 1 tuýp x 50g Reckitt",
    "specification": "Hộp 1 tuýp x 50gam",
    "category1": "Trang thiết bị y tế",
    "category2": "Nói tiết và Sinh lý",
    "registration_num": "",
    "price": 120000,
    "original_price": 120000,
    "image": "assets/placeholder.png",
    "in_stock": true,
    "rating": 4.7,
    "sold_count": 117
  },
  {
    "id": 167,
    "name": "Gel bôi trơn cao cấp Sagami orginal Tuýp 60g",
    "specification": "Hộp 1 tuýp 60g",
    "category1": "Trang thiết bị y tế",
    "category2": "Nội tiết và Sinh lý",
    "registration_num": "220001228/PCBA-HCM",
    "price": 110000,
    "original_price": 130000,
    "image": "assets/placeholder.png",
    "in_stock": true,
    "rating": 4.1,
    "sold_count": 21
  },
  {
    "id": 168,
    "name": "Gel bôi trơn cao cấp Sagami original Hôp 1 tuýp x 60g",
    "specification": "Hộp 1 tuýp 60g",
    "category1": "Trang thiết bị y tế",
    "category2": "Nội tiết và Sinh lý",
    "registration_num": "220001228/PCBA-HCM",
    "price": 180000,
    "original_price": 180000,
    "image": "assets/placeholder.png",
    "in_stock": true,
    "rating": 4.3,
    "sold_count": 153
  },
  {
    "id": 169,
    "name": "Găng tay y tế có bột size S Hộp 100 cái Khánh Linh",
    "specification": "Hộp 100 cái",
    "category1": "Trang thiết bị y tế",
    "category2": "Máy móc và thiết bị đo",
    "registration_num": "",
    "price": 130000,
    "original_price": 130000,
    "image": "assets/placeholder.png",
    "in_stock": true,
    "rating": 4.8,
    "sold_count": 48
  }
]